cijoe/cli/__init__.py
cijoe/cli/__main__.py
cijoe/cli/cli.py
cijoe/core/__init__.py
cijoe/core/analyser.py
cijoe/core/command.py
cijoe/core/errors.py
cijoe/core/misc.py
cijoe/core/processing.py
cijoe/core/resources.py
cijoe/core/transport.py
cijoe/core/auxiliary/__init__.py
cijoe/core/auxiliary/cijoe-completions
cijoe/core/auxiliary/example.perfreq
cijoe/core/configs/__init__.py
cijoe/core/configs/example_config_default.toml
cijoe/core/configs/example_config_get_put.toml
cijoe/core/configs/example_config_testrunner.toml
cijoe/core/configs/transport-ssh.toml
cijoe/core/scripts/__init__.py
cijoe/core/scripts/cmdrunner.py
cijoe/core/scripts/example_script_default.py
cijoe/core/scripts/example_script_testrunner.py
cijoe/core/scripts/get.py
cijoe/core/scripts/put.py
cijoe/core/scripts/reporter.py
cijoe/core/scripts/repository_prep.py
cijoe/core/scripts/testrunner.py
cijoe/core/scripts/wait_for_transport.py
cijoe/core/templates/__init__.py
cijoe/core/templates/example-tmp-workflow.yaml.jinja2
cijoe/core/templates/report-workflow.html.jinja2
cijoe/core/workflows/__init__.py
cijoe/core/workflows/example_workflow_default.yaml
cijoe/core/workflows/example_workflow_get_put.yaml
cijoe/core/workflows/example_workflow_testrunner.yaml
cijoe/core/worklets/__init__.py
cijoe/linux/__init__.py
cijoe/linux/null_blk.py
cijoe/linux/configs/__init__.py
cijoe/linux/configs/example_config_build_kdebs.toml
cijoe/linux/configs/example_config_null_blk.toml
cijoe/linux/scripts/__init__.py
cijoe/linux/scripts/build_kdebs.py
cijoe/linux/scripts/null_blk.py
cijoe/linux/scripts/sysinfo.py
cijoe/linux/workflows/__init__.py
cijoe/linux/workflows/example_workflow_build_kdebs.yaml
cijoe/linux/workflows/example_workflow_null_blk.yaml
cijoe/pytest_plugin/__init__.py
cijoe/pytest_plugin/hooks_and_fixtures.py
cijoe/qemu/__init__.py
cijoe/qemu/wrapper.py
cijoe/qemu/auxiliary/__init__.py
cijoe/qemu/configs/__init__.py
cijoe/qemu/configs/example_config_build.toml
cijoe-0.9.58.dist-info/licenses/LICENSE
cijoe-0.9.58.dist-info/METADATA
cijoe-0.9.58.dist-info/WHEEL
cijoe-0.9.58.dist-info/entry_points.txt
cijoe-0.9.58.dist-info/top_level.txt
cijoe-0.9.58.dist-info/RECORD
