Metadata-Version: 2.4
Name: cijoe
Version: 0.9.58
Summary: A loosely coupled approach to systems development and testing
Author-email: "Simon A. F. Lund" <os@safl.dk>
Maintainer-email: "Simon A. F. Lund" <os@safl.dk>
License: BSD 3-Clause License
Project-URL: homepage, https://cijoe.readthedocs.io/
Project-URL: documentation, https://cijoe.readthedocs.io/
Project-URL: repository, https://github.com/refenv/cijoe
Project-URL: changelog, https://github.com/refenv/cijoe/blob/main/CHANGELOG.md
Keywords: systems,development,testing
Classifier: Development Status :: 4 - Beta
Classifier: Environment :: Console
Classifier: Framework :: Pytest
Classifier: Intended Audience :: Developers
Classifier: Intended Audience :: System Administrators
Classifier: License :: OSI Approved :: BSD License
Classifier: Programming Language :: Python
Classifier: Topic :: Software Development :: Testing
Classifier: Topic :: Software Development
Classifier: Topic :: Text Processing
Classifier: Topic :: Utilities
Requires-Python: >=3.9
License-File: LICENSE
Requires-Dist: jinja2
Requires-Dist: paramiko
Requires-Dist: pytest
Requires-Dist: pytest-random-order>=1.0.0
Requires-Dist: pytest-reportlog
Requires-Dist: pyyaml
Requires-Dist: requests
Requires-Dist: psutil
Requires-Dist: scp
Requires-Dist: tomli>=1.1.0; python_version < "3.11"
Requires-Dist: tomli-w
Requires-Dist: watchdog
Dynamic: license-file
